{
  "title": "SONiC Switch Telemetry",
  "uid": "sonic-telemetry-v2",
  "schemaVersion": 38,
  "version": 1,
  "refresh": "10s",
  "time": { "from": "now-30m", "to": "now" },
  "panels": [
    { "type": "text", "id": 1, "gridPos": { "x": 0, "y": 0, "w": 24, "h": 2 }, "options": { "mode": "markdown", "content": "# 🌡️ Temperature" } },
    { "type": "gauge", "id": 2, "title": "Temperature — All Sensors (°C)", "gridPos": { "x": 0, "y": 2, "w": 24, "h": 8 }, "datasource": { "type": "prometheus", "uid": "prometheus" }, "options": { "reduceOptions": { "calcs": ["lastNotNull"] }, "orientation": "auto", "showThresholdLabels": true, "showThresholdMarkers": true, "minVizWidth": 75 }, "fieldConfig": { "defaults": { "unit": "celsius", "min": 0, "max": 100, "thresholds": { "mode": "absolute", "steps": [{ "color": "green", "value": null }, { "color": "yellow", "value": 65 }, { "color": "red", "value": 80 }] }, "displayName": "${__field.labels.sensor}" }, "overrides": [] }, "targets": [{ "datasource": { "type": "prometheus", "uid": "prometheus" }, "expr": "sonic_temperature_celsius{target=\"switch1\"}", "legendFormat": "{{sensor}}", "refId": "A" }] },
    { "type": "timeseries", "id": 3, "title": "Temperature Over Time (°C)", "gridPos": { "x": 0, "y": 10, "w": 24, "h": 8 }, "datasource": { "type": "prometheus", "uid": "prometheus" }, "options": { "tooltip": { "mode": "multi" }, "legend": { "displayMode": "table", "placement": "bottom" } }, "fieldConfig": { "defaults": { "unit": "celsius", "custom": { "lineWidth": 2, "fillOpacity": 10 }, "thresholds": { "mode": "absolute", "steps": [{ "color": "green", "value": null }, { "color": "yellow", "value": 65 }, { "color": "red", "value": 80 }] } }, "overrides": [] }, "targets": [{ "datasource": { "type": "prometheus", "uid": "prometheus" }, "expr": "sonic_temperature_celsius{target=\"switch1\"}", "legendFormat": "{{sensor}}", "refId": "A" }] },
    { "type": "text", "id": 4, "gridPos": { "x": 0, "y": 18, "w": 24, "h": 2 }, "options": { "mode": "markdown", "content": "# 🔌 Interface Status" } },
    { "type": "stat", "id": 5, "title": "Ports UP", "gridPos": { "x": 0, "y": 20, "w": 4, "h": 4 }, "datasource": { "type": "prometheus", "uid": "prometheus" }, "options": { "reduceOptions": { "calcs": ["lastNotNull"] }, "colorMode": "background", "graphMode": "none", "textMode": "auto" }, "fieldConfig": { "defaults": { "unit": "short", "thresholds": { "mode": "absolute", "steps": [{ "color": "green", "value": null }] } }, "overrides": [] }, "targets": [{ "datasource": { "type": "prometheus", "uid": "prometheus" }, "expr": "count(sonic__openconfig_interfaces_interfaces_interface_state_openconfig_interfaces_state_admin_status{admin_status=\"UP\",oper_status=\"UP\"})", "legendFormat": "UP", "refId": "A" }] },
    { "type": "stat", "id": 6, "title": "Ports DOWN", "gridPos": { "x": 4, "y": 20, "w": 4, "h": 4 }, "datasource": { "type": "prometheus", "uid": "prometheus" }, "options": { "reduceOptions": { "calcs": ["lastNotNull"] }, "colorMode": "background", "graphMode": "none", "textMode": "auto" }, "fieldConfig": { "defaults": { "unit": "short", "thresholds": { "mode": "absolute", "steps": [{ "color": "red", "value": null }] } }, "overrides": [] }, "targets": [{ "datasource": { "type": "prometheus", "uid": "prometheus" }, "expr": "count(sonic__openconfig_interfaces_interfaces_interface_state_openconfig_interfaces_state_admin_status{admin_status=\"UP\",oper_status=\"DOWN\"})", "legendFormat": "DOWN", "refId": "A" }] },
    { "type": "table", "id": 7, "title": "Interface Status Table", "gridPos": { "x": 8, "y": 20, "w": 16, "h": 8 }, "datasource": { "type": "prometheus", "uid": "prometheus" }, "options": { "sortBy": [{ "displayName": "Interface", "desc": false }], "footer": { "show": false } }, "fieldConfig": { "defaults": { "custom": { "align": "left" } }, "overrides": [{ "matcher": { "id": "byName", "options": "oper_status" }, "properties": [{ "id": "custom.displayMode", "value": "color-background" }, { "id": "mappings", "value": [{ "type": "value", "options": { "UP": { "color": "green", "index": 0 }, "DOWN": { "color": "red", "index": 1 } } }] }] }] }, "transformations": [{ "id": "labelsToFields", "options": { "mode": "columns" } }, { "id": "organize", "options": { "excludeByName": { "Time": true, "Value": true, "job": true, "instance": true, "subscription_name": true, "subscription_target": true, "source": true, "target": true, "name": true }, "renameByName": { "interface_name": "Interface", "admin_status": "Admin", "oper_status": "Oper Status" } } }], "targets": [{ "datasource": { "type": "prometheus", "uid": "prometheus" }, "expr": "sonic__openconfig_interfaces_interfaces_interface_state_openconfig_interfaces_state_admin_status", "legendFormat": "", "refId": "A", "instant": true }] },
    { "type": "text", "id": 8, "gridPos": { "x": 0, "y": 28, "w": 24, "h": 2 }, "options": { "mode": "markdown", "content": "# 📊 Interface Traffic" } },
    { "type": "timeseries", "id": 9, "title": "Traffic In (bytes/s)", "gridPos": { "x": 0, "y": 30, "w": 12, "h": 8 }, "datasource": { "type": "prometheus", "uid": "prometheus" }, "options": { "tooltip": { "mode": "multi" }, "legend": { "displayMode": "list", "placement": "bottom" } }, "fieldConfig": { "defaults": { "unit": "Bps", "custom": { "lineWidth": 1, "fillOpacity": 10 } }, "overrides": [] }, "targets": [{ "datasource": { "type": "prometheus", "uid": "prometheus" }, "expr": "rate(sonic__openconfig_interfaces_interfaces_interface_state_openconfig_interfaces_state_counters_in_octets[1m])", "legendFormat": "{{interface_name}}", "refId": "A" }] },
    { "type": "timeseries", "id": 10, "title": "Traffic Out (bytes/s)", "gridPos": { "x": 12, "y": 30, "w": 12, "h": 8 }, "datasource": { "type": "prometheus", "uid": "prometheus" }, "options": { "tooltip": { "mode": "multi" }, "legend": { "displayMode": "list", "placement": "bottom" } }, "fieldConfig": { "defaults": { "unit": "Bps", "custom": { "lineWidth": 1, "fillOpacity": 10 } }, "overrides": [] }, "targets": [{ "datasource": { "type": "prometheus", "uid": "prometheus" }, "expr": "rate(sonic__openconfig_interfaces_interfaces_interface_state_openconfig_interfaces_state_counters_out_octets[1m])", "legendFormat": "{{interface_name}}", "refId": "A" }] },
    { "type": "text", "id": 11, "gridPos": { "x": 0, "y": 38, "w": 24, "h": 2 }, "options": { "mode": "markdown", "content": "# ⚠️ Errors & Discards" } },
    { "type": "timeseries", "id": 12, "title": "In Errors & Discards (packets/s)", "gridPos": { "x": 0, "y": 40, "w": 12, "h": 8 }, "datasource": { "type": "prometheus", "uid": "prometheus" }, "options": { "tooltip": { "mode": "multi" }, "legend": { "displayMode": "list", "placement": "bottom" } }, "fieldConfig": { "defaults": { "unit": "pps", "custom": { "lineWidth": 1, "fillOpacity": 10 } }, "overrides": [] }, "targets": [{ "datasource": { "type": "prometheus", "uid": "prometheus" }, "expr": "rate(sonic__openconfig_interfaces_interfaces_interface_state_openconfig_interfaces_state_counters_in_errors[1m]) > 0", "legendFormat": "in-errors {{interface_name}}", "refId": "A" }, { "datasource": { "type": "prometheus", "uid": "prometheus" }, "expr": "rate(sonic__openconfig_interfaces_interfaces_interface_state_openconfig_interfaces_state_counters_in_discards[1m]) > 0", "legendFormat": "in-discards {{interface_name}}", "refId": "B" }] },
    { "type": "timeseries", "id": 13, "title": "Out Errors & Discards (packets/s)", "gridPos": { "x": 12, "y": 40, "w": 12, "h": 8 }, "datasource": { "type": "prometheus", "uid": "prometheus" }, "options": { "tooltip": { "mode": "multi" }, "legend": { "displayMode": "list", "placement": "bottom" } }, "fieldConfig": { "defaults": { "unit": "pps", "custom": { "lineWidth": 1, "fillOpacity": 10 } }, "overrides": [] }, "targets": [{ "datasource": { "type": "prometheus", "uid": "prometheus" }, "expr": "rate(sonic__openconfig_interfaces_interfaces_interface_state_openconfig_interfaces_state_counters_out_errors[1m]) > 0", "legendFormat": "out-errors {{interface_name}}", "refId": "A" }, { "datasource": { "type": "prometheus", "uid": "prometheus" }, "expr": "rate(sonic__openconfig_interfaces_interfaces_interface_state_openconfig_interfaces_state_counters_out_discards[1m]) > 0", "legendFormat": "out-discards {{interface_name}}", "refId": "B" }] },
    { "type": "table", "id": 14, "title": "Error Summary Table", "gridPos": { "x": 0, "y": 48, "w": 24, "h": 8 }, "datasource": { "type": "prometheus", "uid": "prometheus" }, "options": { "footer": { "show": false } }, "fieldConfig": { "defaults": { "unit": "short", "custom": { "align": "left" } }, "overrides": [{ "matcher": { "id": "byRegexp", "options": ".*error.*|.*discard.*" }, "properties": [{ "id": "custom.displayMode", "value": "color-background" }, { "id": "thresholds", "value": { "mode": "absolute", "steps": [{ "color": "green", "value": null }, { "color": "red", "value": 1 }] } }] }] }, "transformations": [{ "id": "labelsToFields", "options": { "mode": "columns" } }, { "id": "organize", "options": { "excludeByName": { "Time": true, "job": true, "instance": true, "subscription_name": true, "subscription_target": true, "source": true, "target": true, "name": true }, "renameByName": { "interface_name": "Interface" } } }], "targets": [{ "datasource": { "type": "prometheus", "uid": "prometheus" }, "expr": "sonic__openconfig_interfaces_interfaces_interface_state_openconfig_interfaces_state_counters_in_errors", "legendFormat": "in-errors", "refId": "A", "instant": true }, { "datasource": { "type": "prometheus", "uid": "prometheus" }, "expr": "sonic__openconfig_interfaces_interfaces_interface_state_openconfig_interfaces_state_counters_in_discards", "legendFormat": "in-discards", "refId": "B", "instant": true }, { "datasource": { "type": "prometheus", "uid": "prometheus" }, "expr": "sonic__openconfig_interfaces_interfaces_interface_state_openconfig_interfaces_state_counters_out_errors", "legendFormat": "out-errors", "refId": "C", "instant": true }, { "datasource": { "type": "prometheus", "uid": "prometheus" }, "expr": "sonic__openconfig_interfaces_interfaces_interface_state_openconfig_interfaces_state_counters_out_discards", "legendFormat": "out-discards", "refId": "D", "instant": true }] }
  ]
}
